{
    "MoveToGoal": {
        "checkpoints": [
            {
                "steps": 76332,
                "file_path": "results\\TestParameters\\MoveToGoal\\MoveToGoal-76332.onnx",
                "reward": null,
                "creation_time": 1705361746.469089,
                "auxillary_file_paths": [
                    "results\\TestParameters\\MoveToGoal\\MoveToGoal-76332.pt"
                ]
            }
        ],
        "final_checkpoint": {
            "steps": 76332,
            "file_path": "results\\TestParameters\\MoveToGoal.onnx",
            "reward": null,
            "creation_time": 1705361746.469089,
            "auxillary_file_paths": [
                "results\\TestParameters\\MoveToGoal\\MoveToGoal-76332.pt"
            ]
        }
    },
    "metadata": {
        "stats_format_version": "0.3.0",
        "mlagents_version": "0.30.0",
        "torch_version": "2.1.2+cpu"
    }
}